[
    {
        "person_id": 1868,
        "company": "Р Фарм",
        "phones": [
            "8 (376) 624-64-47",
            "8 (911) 138-52-80",
            "8 (581) 716-75-55",
            "8 (651) 773-45-53",
            "8 (897) 900-94-85",
            "8 (800) 550-70-77"
        ]
    },
    {
        "person_id": 1873,
        "company": "Веро Фарма",
        "phones": [
            "8 (720) 791-33-31",
            "8 (651) 120-25-07",
            "8 (084) 604-76-58",
            "8 (395) 702-09-81",
            "8 (638) 245-38-07",
            "8 (394) 806-37-91",
            "8 (543) 601-60-60",
            "8 (391) 113-31-61",
            "8 (961) 833-50-17",
            "8 (754) 247-28-72",
            "8 (390) 596-51-81",
            "8 (876) 710-02-11",
            "8 (037) 868-03-37",
            "8 (390) 192-99-71",
            "8 (531) 652-53-71",
            "8 (103) 118-50-36",
            "8 (389) 976-94-61",
            "8 (147) 859-61-71",
            "8 (084) 116-08-70",
            "8 (389) 243-50-01",
            "8 (878) 505-02-66",
            "8 (747) 653-01-48",
            "8 (744) 497-12-19"
        ]
    },
    {
        "person_id": 1877,
        "company": "Синтез",
        "phones": [
            "8 (302) 490-70-55",
            "8 (541) 563-11-96",
            "8 (302) 707-37-22",
            "8 (480) 095-58-49",
            "8 (301) 937-37-22",
            "8 (196) 465-76-74",
            "8 (302) 204-03-89",
            "8 (302) 084-03-89",
            "8 (302) 650-70-55",
            "8 (238) 356-19-31",
            "8 (302) 777-37-21",
            "8 (302) 364-03-89",
            "8 (302) 247-37-22",
            "8 (005) 749-35-41",
            "8 (303) 040-70-55",
            "8 (507) 804-36-06"
        ]
    },
    {
        "person_id": 1882,
        "company": "Нижфарм",
        "phones": [
            "8 (333) 333-33-33",
            "8 (888) 888-88-88",
            "8 (571) 428-57-14"
        ]
    },
    {
        "person_id": 1883,
        "company": "Unknown",
        "phones": [
            "8 (817) 584-51-43"
        ]
    },
    {
        "person_id": 1871,
        "company": "Unknown",
        "phones": [
            "8 (817) 584-51-43"
        ]
    },
    {
        "person_id": 1870,
        "company": "Unknown",
        "phones": [
            "8 (817) 584-51-43"
        ]
    },
    {
        "person_id": 1876,
        "company": "Unknown",
        "phones": [
            "8 (817) 584-51-43"
        ]
    },
    {
        "person_id": 1880,
        "company": "Unknown",
        "phones": [
            "8 (817) 584-51-43"
        ]
    },
    {
        "person_id": 1906,
        "company": "Unknown",
        "phones": [
            "8 (817) 584-51-43"
        ]
    },
    {
        "person_id": 1915,
        "company": "Unknown",
        "phones": [
            "8 (817) 584-51-43"
        ]
    },
    {
        "person_id": 1951,
        "company": "Unknown",
        "phones": [
            "8 (817) 584-51-43"
        ]
    },
    {
        "person_id": 1953,
        "company": "Unknown",
        "phones": [
            "8 (817) 584-51-43"
        ]
    },
    {
        "person_id": 1959,
        "company": "Unknown",
        "phones": [
            "8 (817) 584-51-43"
        ]
    },
    {
        "person_id": 1965,
        "company": "Unknown",
        "phones": [
            "8 (817) 584-51-43"
        ]
    },
    {
        "person_id": 1967,
        "company": "Unknown",
        "phones": [
            "8 (817) 584-51-43"
        ]
    },
    {
        "person_id": 1961,
        "company": "Unknown",
        "phones": [
            "8 (817) 584-51-43"
        ]
    },
    {
        "person_id": 1970,
        "company": "Unknown",
        "phones": [
            "8 (817) 584-51-43"
        ]
    },
    {
        "person_id": 1971,
        "company": "Unknown",
        "phones": [
            "8 (817) 584-51-43"
        ]
    },
    {
        "person_id": 1972,
        "company": "Unknown",
        "phones": [
            "8 (817) 584-51-43"
        ]
    },
    {
        "person_id": 1974,
        "company": "Unknown",
        "phones": [
            "8 (817) 584-51-43"
        ]
    },
    {
        "person_id": 1973,
        "company": "Unknown",
        "phones": [
            "8 (817) 584-51-43"
        ]
    },
    {
        "person_id": 1977,
        "company": "Unknown",
        "phones": [
            "8 (817) 584-51-43"
        ]
    },
    {
        "person_id": 1979,
        "company": "Unknown",
        "phones": [
            "8 (817) 584-51-43"
        ]
    },
    {
        "person_id": 1992,
        "company": "Unknown",
        "phones": [
            "8 (817) 584-51-43"
        ]
    },
    {
        "person_id": 1995,
        "company": "Unknown",
        "phones": [
            "8 (817) 584-51-43"
        ]
    },
    {
        "person_id": 1996,
        "company": "Unknown",
        "phones": [
            "8 (817) 584-51-43"
        ]
    },
    {
        "person_id": 2010,
        "company": "Unknown",
        "phones": [
            "8 (817) 584-51-43"
        ]
    },
    {
        "person_id": 2025,
        "company": "Unknown",
        "phones": [
            "8 (817) 584-51-43"
        ]
    },
    {
        "person_id": 2022,
        "company": "Unknown",
        "phones": [
            "8 (817) 584-51-43"
        ]
    },
    {
        "person_id": 2062,
        "company": "Unknown",
        "phones": [
            "8 (817) 584-51-43"
        ]
    },
    {
        "person_id": 2085,
        "company": "Unknown",
        "phones": [
            "8 (817) 584-51-43"
        ]
    },
    {
        "person_id": 2084,
        "company": "Unknown",
        "phones": [
            "8 (817) 584-51-43"
        ]
    },
    {
        "person_id": 2074,
        "company": "Unknown",
        "phones": [
            "8 (817) 584-51-43"
        ]
    },
    {
        "person_id": 2077,
        "company": "Unknown",
        "phones": [
            "8 (817) 584-51-43"
        ]
    },
    {
        "person_id": 2093,
        "company": "Unknown",
        "phones": [
            "8 (817) 584-51-43"
        ]
    },
    {
        "person_id": 2090,
        "company": "Unknown",
        "phones": [
            "8 (817) 584-51-43"
        ]
    },
    {
        "person_id": 2094,
        "company": "Unknown",
        "phones": [
            "8 (817) 584-51-43"
        ]
    },
    {
        "person_id": 2088,
        "company": "Unknown",
        "phones": [
            "8 (817) 584-51-43"
        ]
    },
    {
        "person_id": 2095,
        "company": "Unknown",
        "phones": [
            "8 (817) 584-51-43"
        ]
    },
    {
        "person_id": 2097,
        "company": "Unknown",
        "phones": [
            "8 (817) 584-51-43"
        ]
    },
    {
        "person_id": 2103,
        "company": "Unknown",
        "phones": [
            "8 (817) 584-51-43"
        ]
    },
    {
        "person_id": 2096,
        "company": "Unknown",
        "phones": [
            "8 (817) 584-51-43"
        ]
    },
    {
        "person_id": 2091,
        "company": "Unknown",
        "phones": [
            "8 (817) 584-51-43"
        ]
    },
    {
        "person_id": 2089,
        "company": "Unknown",
        "phones": [
            "8 (817) 584-51-43"
        ]
    },
    {
        "person_id": 2092,
        "company": "Unknown",
        "phones": [
            "8 (817) 584-51-43"
        ]
    },
    {
        "person_id": 2110,
        "company": "Unknown",
        "phones": [
            "8 (817) 584-51-43"
        ]
    },
    {
        "person_id": 2113,
        "company": "Unknown",
        "phones": [
            "8 (817) 584-51-43"
        ]
    },
    {
        "person_id": 2117,
        "company": "Unknown",
        "phones": [
            "8 (817) 584-51-43"
        ]
    },
    {
        "person_id": 2122,
        "company": "Unknown",
        "phones": [
            "8 (817) 584-51-43"
        ]
    },
    {
        "person_id": 2124,
        "company": "Unknown",
        "phones": [
            "8 (817) 584-51-43"
        ]
    },
    {
        "person_id": 2132,
        "company": "Unknown",
        "phones": [
            "8 (817) 584-51-43"
        ]
    },
    {
        "person_id": 2135,
        "company": "Unknown",
        "phones": [
            "8 (817) 584-51-43"
        ]
    },
    {
        "person_id": 2137,
        "company": "Unknown",
        "phones": [
            "8 (817) 584-51-43"
        ]
    },
    {
        "person_id": 2138,
        "company": "Unknown",
        "phones": [
            "8 (817) 584-51-43"
        ]
    },
    {
        "person_id": 2139,
        "company": "Unknown",
        "phones": [
            "8 (817) 584-51-43"
        ]
    },
    {
        "person_id": 2140,
        "company": "Unknown",
        "phones": [
            "8 (817) 584-51-43"
        ]
    },
    {
        "person_id": 2142,
        "company": "Unknown",
        "phones": [
            "8 (817) 584-51-43"
        ]
    },
    {
        "person_id": 2136,
        "company": "Unknown",
        "phones": [
            "8 (817) 584-51-43"
        ]
    },
    {
        "person_id": 2143,
        "company": "Unknown",
        "phones": [
            "8 (817) 584-51-43"
        ]
    },
    {
        "person_id": 2144,
        "company": "Unknown",
        "phones": [
            "8 (817) 584-51-43"
        ]
    },
    {
        "person_id": 2145,
        "company": "Unknown",
        "phones": [
            "8 (817) 584-51-43"
        ]
    },
    {
        "person_id": 2146,
        "company": "Unknown",
        "phones": [
            "8 (817) 584-51-43"
        ]
    },
    {
        "person_id": 2147,
        "company": "Unknown",
        "phones": [
            "8 (817) 584-51-43"
        ]
    },
    {
        "person_id": 2148,
        "company": "Unknown",
        "phones": [
            "8 (817) 584-51-43"
        ]
    },
    {
        "person_id": 2151,
        "company": "Unknown",
        "phones": [
            "8 (817) 584-51-43"
        ]
    },
    {
        "person_id": 2150,
        "company": "Unknown",
        "phones": [
            "8 (817) 584-51-43"
        ]
    },
    {
        "person_id": 2152,
        "company": "Unknown",
        "phones": [
            "8 (817) 584-51-43"
        ]
    },
    {
        "person_id": 2153,
        "company": "Unknown",
        "phones": [
            "8 (817) 584-51-43"
        ]
    },
    {
        "person_id": 2163,
        "company": "Unknown",
        "phones": [
            "8 (817) 584-51-43"
        ]
    },
    {
        "person_id": 2149,
        "company": "Unknown",
        "phones": [
            "8 (817) 584-51-43"
        ]
    },
    {
        "person_id": 2164,
        "company": "Unknown",
        "phones": [
            "8 (817) 584-51-43"
        ]
    },
    {
        "person_id": 2165,
        "company": "Unknown",
        "phones": [
            "8 (817) 584-51-43"
        ]
    },
    {
        "person_id": 2158,
        "company": "Unknown",
        "phones": [
            "8 (817) 584-51-43"
        ]
    },
    {
        "person_id": 2162,
        "company": "Unknown",
        "phones": [
            "8 (817) 584-51-43"
        ]
    },
    {
        "person_id": 2141,
        "company": "Unknown",
        "phones": [
            "8 (817) 584-51-43"
        ]
    },
    {
        "person_id": 2160,
        "company": "Unknown",
        "phones": [
            "8 (817) 584-51-43"
        ]
    },
    {
        "person_id": 2154,
        "company": "Unknown",
        "phones": [
            "8 (817) 584-51-43"
        ]
    },
    {
        "person_id": 2161,
        "company": "Unknown",
        "phones": [
            "8 (817) 584-51-43"
        ]
    },
    {
        "person_id": 2159,
        "company": "Unknown",
        "phones": [
            "8 (817) 584-51-43"
        ]
    },
    {
        "person_id": 2155,
        "company": "Unknown",
        "phones": [
            "8 (817) 584-51-43"
        ]
    },
    {
        "person_id": 2173,
        "company": "Unknown",
        "phones": [
            "8 (817) 584-51-43"
        ]
    },
    {
        "person_id": 2174,
        "company": "Unknown",
        "phones": [
            "8 (817) 584-51-43"
        ]
    },
    {
        "person_id": 2175,
        "company": "Unknown",
        "phones": [
            "8 (817) 584-51-43"
        ]
    },
    {
        "person_id": 2166,
        "company": "Unknown",
        "phones": [
            "8 (817) 584-51-43"
        ]
    },
    {
        "person_id": 2177,
        "company": "Unknown",
        "phones": [
            "8 (817) 584-51-43"
        ]
    },
    {
        "person_id": 2176,
        "company": "Unknown",
        "phones": [
            "8 (817) 584-51-43"
        ]
    },
    {
        "person_id": 2167,
        "company": "Unknown",
        "phones": [
            "8 (817) 584-51-43"
        ]
    },
    {
        "person_id": 2168,
        "company": "Unknown",
        "phones": [
            "8 (817) 584-51-43"
        ]
    },
    {
        "person_id": 2178,
        "company": "Unknown",
        "phones": [
            "8 (817) 584-51-43"
        ]
    },
    {
        "person_id": 2179,
        "company": "Unknown",
        "phones": [
            "8 (817) 584-51-43"
        ]
    },
    {
        "person_id": 2170,
        "company": "Unknown",
        "phones": [
            "8 (817) 584-51-43"
        ]
    },
    {
        "person_id": 2180,
        "company": "Unknown",
        "phones": [
            "8 (817) 584-51-43"
        ]
    },
    {
        "person_id": 2171,
        "company": "Unknown",
        "phones": [
            "8 (817) 584-51-43"
        ]
    },
    {
        "person_id": 2172,
        "company": "Unknown",
        "phones": [
            "8 (817) 584-51-43"
        ]
    },
    {
        "person_id": 2169,
        "company": "Unknown",
        "phones": [
            "8 (817) 584-51-43"
        ]
    },
    {
        "person_id": 2191,
        "company": "Unknown",
        "phones": [
            "8 (817) 584-51-43"
        ]
    },
    {
        "person_id": 2192,
        "company": "Unknown",
        "phones": [
            "8 (817) 584-51-43"
        ]
    },
    {
        "person_id": 2193,
        "company": "Unknown",
        "phones": [
            "8 (817) 584-51-43"
        ]
    },
    {
        "person_id": 2182,
        "company": "Unknown",
        "phones": [
            "8 (817) 584-51-43"
        ]
    },
    {
        "person_id": 2183,
        "company": "Unknown",
        "phones": [
            "8 (817) 584-51-43"
        ]
    },
    {
        "person_id": 2186,
        "company": "Unknown",
        "phones": [
            "8 (817) 584-51-43"
        ]
    },
    {
        "person_id": 2187,
        "company": "Unknown",
        "phones": [
            "8 (817) 584-51-43"
        ]
    },
    {
        "person_id": 2188,
        "company": "Unknown",
        "phones": [
            "8 (817) 584-51-43"
        ]
    },
    {
        "person_id": 2194,
        "company": "Unknown",
        "phones": [
            "8 (817) 584-51-43"
        ]
    },
    {
        "person_id": 2189,
        "company": "Unknown",
        "phones": [
            "8 (817) 584-51-43"
        ]
    },
    {
        "person_id": 2181,
        "company": "Unknown",
        "phones": [
            "8 (817) 584-51-43"
        ]
    },
    {
        "person_id": 2190,
        "company": "Unknown",
        "phones": [
            "8 (817) 584-51-43"
        ]
    },
    {
        "person_id": 2195,
        "company": "Unknown",
        "phones": [
            "8 (817) 584-51-43"
        ]
    },
    {
        "person_id": 2197,
        "company": "Unknown",
        "phones": [
            "8 (817) 584-51-43"
        ]
    },
    {
        "person_id": 2196,
        "company": "Unknown",
        "phones": [
            "8 (817) 584-51-43"
        ]
    },
    {
        "person_id": 2198,
        "company": "Unknown",
        "phones": [
            "8 (817) 584-51-43"
        ]
    },
    {
        "person_id": 2199,
        "company": "Unknown",
        "phones": [
            "8 (817) 584-51-43"
        ]
    },
    {
        "person_id": 2201,
        "company": "Unknown",
        "phones": [
            "8 (817) 584-51-43"
        ]
    },
    {
        "person_id": 2200,
        "company": "Unknown",
        "phones": [
            "8 (817) 584-51-43"
        ]
    },
    {
        "person_id": 1875,
        "company": "Вертекс",
        "phones": [
            "8 (858) 695-65-21",
            "8 (260) 869-56-52",
            "8 (695) 652-17-39",
            "8 (478) 260-86-95"
        ]
    },
    {
        "person_id": 1874,
        "company": "НоваМедика",
        "phones": [
            "8 (025) 502-29-38"
        ]
    }
]